pandas_profiling/__init__.py
ydata_profiling/__init__.py
ydata_profiling/compare_reports.py
ydata_profiling/config.py
ydata_profiling/config_default.yaml
ydata_profiling/config_minimal.yaml
ydata_profiling/expectations_report.py
ydata_profiling/profile_report.py
ydata_profiling/serialize_report.py
ydata_profiling/version.py
ydata_profiling/controller/__init__.py
ydata_profiling/controller/console.py
ydata_profiling/controller/pandas_decorator.py
ydata_profiling/model/__init__.py
ydata_profiling/model/alerts.py
ydata_profiling/model/correlations.py
ydata_profiling/model/dataframe.py
ydata_profiling/model/describe.py
ydata_profiling/model/description.py
ydata_profiling/model/duplicates.py
ydata_profiling/model/expectation_algorithms.py
ydata_profiling/model/handler.py
ydata_profiling/model/missing.py
ydata_profiling/model/pairwise.py
ydata_profiling/model/sample.py
ydata_profiling/model/summarizer.py
ydata_profiling/model/summary.py
ydata_profiling/model/summary_algorithms.py
ydata_profiling/model/table.py
ydata_profiling/model/typeset.py
ydata_profiling/model/typeset_relations.py
ydata_profiling/model/pandas/__init__.py
ydata_profiling/model/pandas/correlations_pandas.py
ydata_profiling/model/pandas/dataframe_pandas.py
ydata_profiling/model/pandas/describe_boolean_pandas.py
ydata_profiling/model/pandas/describe_categorical_pandas.py
ydata_profiling/model/pandas/describe_counts_pandas.py
ydata_profiling/model/pandas/describe_date_pandas.py
ydata_profiling/model/pandas/describe_file_pandas.py
ydata_profiling/model/pandas/describe_generic_pandas.py
ydata_profiling/model/pandas/describe_image_pandas.py
ydata_profiling/model/pandas/describe_numeric_pandas.py
ydata_profiling/model/pandas/describe_path_pandas.py
ydata_profiling/model/pandas/describe_supported_pandas.py
ydata_profiling/model/pandas/describe_text_pandas.py
ydata_profiling/model/pandas/describe_timeseries_pandas.py
ydata_profiling/model/pandas/describe_url_pandas.py
ydata_profiling_thorrester-0.0.0.dist-info/LICENSE
ydata_profiling_thorrester-0.0.0.dist-info/METADATA
ydata_profiling_thorrester-0.0.0.dist-info/WHEEL
ydata_profiling_thorrester-0.0.0.dist-info/entry_points.txt
ydata_profiling_thorrester-0.0.0.dist-info/top_level.txt
ydata_profiling_thorrester-0.0.0.dist-info/RECORD
