Metadata-Version: 2.1
Name: ydata-profiling-thorrester
Version: 0.0.0
Summary: Generate profile report for pandas DataFrame
Home-page: https://github.com/thorrester/ydata-profiling
Author: YData Labs Inc
Author-email: opensource@ydata.ai
License: MIT
Keywords: pandas data-science data-analysis python jupyter ipython
Classifier: Development Status :: 5 - Production/Stable
Classifier: Topic :: Software Development :: Build Tools
Classifier: License :: OSI Approved :: MIT License
Classifier: Environment :: Console
Classifier: Operating System :: OS Independent
Classifier: Intended Audience :: Science/Research
Classifier: Intended Audience :: Developers
Classifier: Intended Audience :: Financial and Insurance Industry
Classifier: Intended Audience :: Healthcare Industry
Classifier: Topic :: Scientific/Engineering
Classifier: Framework :: IPython
Classifier: Programming Language :: Python :: 3
Classifier: Programming Language :: Python :: 3.7
Classifier: Programming Language :: Python :: 3.8
Classifier: Programming Language :: Python :: 3.9
Classifier: Programming Language :: Python :: 3.10
Requires-Python: >=3.7, <3.12
License-File: LICENSE
Requires-Dist: scipy <1.11,>=1.4.1
Requires-Dist: pandas !=1.4.0,<2.1,>1.1
Requires-Dist: matplotlib <4,>=3.2
Requires-Dist: pydantic >=1.8.1
Requires-Dist: PyYAML <6.1,>=5.0.0
Requires-Dist: jinja2 <3.2,>=2.11.1
Requires-Dist: visions[type_image_path] ==0.7.5
Requires-Dist: numpy <1.24,>=1.16.0
Requires-Dist: htmlmin ==0.1.12
Requires-Dist: phik <0.13,>=0.11.1
Requires-Dist: requests <3,>=2.24.0
Requires-Dist: tqdm <5,>=4.48.2
Requires-Dist: seaborn <0.13,>=0.10.1
Requires-Dist: multimethod <2,>=1.4
Requires-Dist: statsmodels <1,>=0.13.2
Requires-Dist: typeguard <3,>=2.13.2
Requires-Dist: imagehash ==4.3.1
Requires-Dist: wordcloud >=1.9.1
Requires-Dist: dacite >=1.8
Provides-Extra: notebook
Requires-Dist: jupyter-client >=5.3.4 ; extra == 'notebook'
Requires-Dist: jupyter-core >=4.6.3 ; extra == 'notebook'
Requires-Dist: ipywidgets >=7.5.1 ; extra == 'notebook'
Provides-Extra: unicode
Requires-Dist: tangled-up-in-unicode ==0.2.0 ; extra == 'unicode'
